plannerbenchmark/__init__.py
plannerbenchmark/assets/boxer.urdf
plannerbenchmark/assets/meshes/collision/chassis_link.STL
plannerbenchmark/assets/meshes/collision/extrusion.stl
plannerbenchmark/assets/meshes/collision/finger.stl
plannerbenchmark/assets/meshes/collision/hand.stl
plannerbenchmark/assets/meshes/collision/internal_link.STL
plannerbenchmark/assets/meshes/collision/lift_link.STL
plannerbenchmark/assets/meshes/collision/link0.stl
plannerbenchmark/assets/meshes/collision/link1.stl
plannerbenchmark/assets/meshes/collision/link2.stl
plannerbenchmark/assets/meshes/collision/link3.stl
plannerbenchmark/assets/meshes/collision/link4.stl
plannerbenchmark/assets/meshes/collision/link5.stl
plannerbenchmark/assets/meshes/collision/link6.stl
plannerbenchmark/assets/meshes/collision/link7.stl
plannerbenchmark/assets/meshes/collision/rotacastor_left_link.STL
plannerbenchmark/assets/meshes/collision/rotacastor_right_link.STL
plannerbenchmark/assets/meshes/collision/top_plate.stl
plannerbenchmark/assets/meshes/collision/top_plate_collision.stl
plannerbenchmark/assets/meshes/collision/wheel_left_link.STL
plannerbenchmark/assets/meshes/collision/wheel_right_link.STL
plannerbenchmark/assets/meshes/visual/chassis_link.dae
plannerbenchmark/assets/meshes/visual/colors.png
plannerbenchmark/assets/meshes/visual/finger.mtl
plannerbenchmark/assets/meshes/visual/finger.obj
plannerbenchmark/assets/meshes/visual/hand.mtl
plannerbenchmark/assets/meshes/visual/hand.obj
plannerbenchmark/assets/meshes/visual/internal_link.dae
plannerbenchmark/assets/meshes/visual/lift_link.dae
plannerbenchmark/assets/meshes/visual/link0.dae
plannerbenchmark/assets/meshes/visual/link1.mtl
plannerbenchmark/assets/meshes/visual/link1.obj
plannerbenchmark/assets/meshes/visual/link2.mtl
plannerbenchmark/assets/meshes/visual/link2.obj
plannerbenchmark/assets/meshes/visual/link3.mtl
plannerbenchmark/assets/meshes/visual/link3.obj
plannerbenchmark/assets/meshes/visual/link4.mtl
plannerbenchmark-1.1.1.dist-info/entry_points.txt
plannerbenchmark-1.1.1.dist-info/WHEEL
plannerbenchmark-1.1.1.dist-info/METADATA
plannerbenchmark-1.1.1.dist-info/LICENSE
plannerbenchmark-1.1.1.dist-info/RECORD
