Metadata-Version: 2.1
Name: plannerbenchmark
Version: 1.1.1
Summary: Benchmark suite for local planner in dynamic environments. Multiple planners can be compared on different kinematic chains in different environment. The suite is highly extendable for new planners, robots and environments.
Home-page: https://maxspahn.github.io/localPlannerBench/
License: GPL-3.0-or-later
Keywords: robotics,motion-planning,benchmark
Author: Max Spahn
Author-email: m.spahn@tudelft.nl
Maintainer: Max Spahn
Maintainer-email: m.spahn@tudelft.nl
Requires-Python: >=3.8,<3.10
Classifier: License :: OSI Approved :: GNU General Public License v3 or later (GPLv3+)
Classifier: Programming Language :: Python :: 3
Classifier: Programming Language :: Python :: 3.8
Classifier: Programming Language :: Python :: 3.9
Provides-Extra: fabric
Provides-Extra: mpc
Requires-Dist: fabrics (>=0.6.2,<0.7.0) ; extra == "fabric"
Requires-Dist: forwardkinematics (>=1.1.1,<2.0.0)
Requires-Dist: robotmpcs (>=0.2.1,<0.3.0) ; extra == "mpc"
Requires-Dist: urdfenvs (>=0.7.1,<0.8.0)
Project-URL: Documentation, https://maxspahn.github.io/localPlannerBench/
Project-URL: Repository, https://github.com/maxspahn/localPlannerBench
